EMU27/firmware/spi_slave.sv
`timescale 1ns / 1ns
`default_nettype none

module spi_slave
  #(
    parameter ADDR_WIDTH = 18,
    parameter DATA_WIDTH = 8
    )
  (
   input cs_n,
   input sck,
   input sdi,
   output wire sdo,
   output reg sdoe,

   output reg [ADDR_WIDTH-1:0] addro,
   output reg addroe,

   output reg [DATA_WIDTH-1:0] datao,
   input wire [DATA_WIDTH-1:0] datai,
   output reg dataoe,

   output reg oe_n,
   output reg we_n,
   output wire ce_n
   );

  reg [DATA_WIDTH-2:0] shiftreg = 0;
  wire [DATA_WIDTH-1:0] curr = { shiftreg, sdi };

  reg [DATA_WIDTH-2:0] idx;

  reg rw = 0;

  reg [DATA_WIDTH-1:0] datahold;

  assign sdo = datahold[DATA_WIDTH-1];

  assign ce_n = oe_n && we_n;

  always_ff @(posedge cs_n or posedge sck) begin
    if (cs_n) begin
      idx <= 0;
      rw <= 0;
      addro <= 0;
      addroe <= 0;
      datao <= 0;
      dataoe <= 0;
      datahold <= 0;
      shiftreg <= 0;
      sdoe <= 0;
      oe_n <= 1;

    end else begin
      addroe <= 0;
      dataoe <= 0;

      oe_n <= 1;
      sdoe <= 0;

      if (idx == 7) begin
        rw <= curr[7];
        addro[23:16] <= curr[7:0];
      end else if (idx == 15) begin
        addro[15:8] <= curr[7:0];
      end else if (idx == 23) begin
        addro[7:0] <= curr[7:0];
      end else if (idx == 31) begin
        if (rw)
          addro <= addro + 1;
      end else if (idx == 39) begin
        addro <= addro + 1;
      end

      if (rw) begin
        // Read cycle
        if (idx == 23 || idx == 31 || idx == 39) begin
          addroe <= 1;
          oe_n <= 0;
        end

        if (idx >= 24) begin
          sdoe <= 1;
        end
      end else begin
        // Write cycle
        if (idx == 31 || idx == 39) begin
          datao <= curr;
          addroe <= 1;
          dataoe <= 1;
        end
      end

      if (idx == 39) begin
        idx <= 32;
      end else begin
        idx <= idx + 1;
      end

      shiftreg = curr[6:0];
    end
  end

  always @(posedge cs_n or negedge sck) begin
    if (cs_n) begin
      we_n <= 1;
    end else begin
      we_n <= 1;
      if (dataoe) begin
        we_n <= 0;
      end
      if (!oe_n) begin
        datahold <= datai;
      end else begin
        datahold <= { datahold[6:0], 1'b0 };
      end
    end
  end

endmodule

`default_nettype wire

EMU27/firmware/wrap_spi_slave.v
`timescale 1ns / 1ns
`default_nettype none

module wrap_spi_slave
  #(
    parameter ADDR_WIDTH = 18,
    parameter DATA_WIDTH = 8
    )
  (
   );

  // SPI bus
  wire sck;
  wire cs_n;
  wire sdi;
  wire sdo;
  wire sdoe;

  // EEPROM bus
  wire [ADDR_WIDTH-1:0] addr;
  wire [DATA_WIDTH-1:0] data;

  wire [ADDR_WIDTH-1:0] addro;
  wire addroe;

  wire [DATA_WIDTH-1:0] datao;
  wire dataoe;

  wire oe_n;
  wire we_n;

  // Nice buses that can be viewed in gtkwave

  wire sd = sdoe ? sdo : sdi;

  assign addr = addroe ? addro : 18'hxxxxx;
  assign data = dataoe ? datao : oe_n ? 8'hxx : addr[7:0];

  // DUT
  spi_slave
    #(
      .ADDR_WIDTH(ADDR_WIDTH),
      .DATA_WIDTH(DATA_WIDTH)
      )
  u
    (
     .sck(sck),
     .cs_n(cs_n),
     .sdi(sd),
     .sdo(sdo),
     .sdoe(sdoe),

     .addro(addro),
     .addroe(addroe),
     .datao(datao),
     .dataoe(dataoe),
     .datai(data),

     .we_n(we_n),
     .oe_n(oe_n)
     );

`ifdef COCOTB_SIM
initial begin
  $dumpfile ("dump.vcd");
  $dumpvars(0);
  #1;
end

always @(negedge we_n) begin
  $displayh("EPROM WRITE ", addr, ": ", data);
end

always @(negedge oe_n) begin
  $displayh("EPROM READ ", addr);
end

`endif

endmodule

`default_nettype wire

EMU27/firmware/dump.vcd
$date
	Tue May 24 14:41:44 2022
$end
$version
	Icarus Verilog
$end
$timescale
	1ps
$end
$scope module wrap_spi_slave $end
$var wire 1 ! cs_n $end
$var wire 1 " sck $end
$var wire 1 # sdi $end
$var wire 1 $ we_n $end
$var wire 1 % sdoe $end
$var wire 1 & sdo $end
$var wire 1 ' sd $end
$var wire 1 ( oe_n $end
$var wire 1 ) dataoe $end
$var wire 8 * datao [7:0] $end
$var wire 8 + data [7:0] $end
$var wire 1 , addroe $end
$var wire 18 - addro [17:0] $end
$var wire 18 . addr [17:0] $end
$scope module u $end
$var wire 1 / ce_n $end
$var wire 1 ! cs_n $end
$var wire 8 0 datai [7:0] $end
$var wire 1 " sck $end
$var wire 1 ' sdi $end
$var wire 1 & sdo $end
$var wire 8 1 curr [7:0] $end
$var reg 18 2 addro [17:0] $end
$var reg 1 , addroe $end
$var reg 8 3 datahold [7:0] $end
$var reg 8 4 datao [7:0] $end
$var reg 1 ) dataoe $end
$var reg 7 5 idx [6:0] $end
$var reg 1 ( oe_n $end
$var reg 1 6 rw $end
$var reg 1 % sdoe $end
$var reg 7 7 shiftreg [6:0] $end
$var reg 1 $ we_n $end
$upscope $end
$upscope $end
$enddefinitions $end
#0
$dumpvars
b0 7
06
bx 5
bx 4
bx 3
bx 2
b0x 1
bx 0
x/
bx .
bx -
x,
bx +
bx *
x)
x(
x'
x&
x%
x$
z#
z"
z!
$end
#2000
1/
b0 1
0'
0&
1$
1(
0%
b0 3
0)
b0 *
b0 4
0,
b0 -
b0 2
b0 5
1!
1"
0#
#8000
0"
#10000
1"
#12000
0"
#14000
1"
#16000
0"
#18000
0!
#20000
b1 5
1"
#22000
0"
#24000
b10 5
1"
#26000
0"
#28000
b11 5
1"
#30000
0"
#32000
b100 5
1"
#34000
0"
#36000
b101 5
1"
#38000
0"
#40000
b110 5
1"
#42000
0"
#44000
b111 5
1"
#46000
b1 1
1'
0"
1#
#48000
b1000 5
b10000000000000000 -
b10000000000000000 2
b11 1
b1 7
1"
#50000
b10 1
0'
0"
0#
#52000
b1001 5
b100 1
b10 7
1"
#54000
0"
#56000
b1010 5
b1000 1
b100 7
1"
#58000
b1001 1
1'
0"
1#
#60000
b1011 5
b10011 1
b1001 7
1"
#62000
b10010 1
0'
0"
0#
#64000
b1100 5
b100100 1
b10010 7
1"
#66000
0"
#68000
b1101 5
b1001000 1
b100100 7
1"
#70000
0"
#72000
b1110 5
b10010000 1
b1001000 7
1"
#74000
b10010001 1
1'
0"
1#
#76000
b1111 5
b100011 1
b10001 7
1"
#78000
0"
#80000
b10000 5
b10010001100000000 -
b10010001100000000 2
b1000111 1
b100011 7
1"
#82000
b1000110 1
0'
0"
0#
#84000
b10001 5
b10001100 1
b1000110 7
1"
#86000
b10001101 1
1'
0"
1#
#88000
b10010 5
b11011 1
b1101 7
1"
#90000
b11010 1
0'
0"
0#
#92000
b10011 5
b110100 1
b11010 7
1"
#94000
0"
#96000
b10100 5
b1101000 1
b110100 7
1"
#98000
0"
#100000
b10101 5
b11010000 1
b1101000 7
1"
#102000
b11010001 1
1'
0"
1#
#104000
b10110 5
b10100011 1
b1010001 7
1"
#106000
b10100010 1
0'
0"
0#
#108000
b10111 5
b1000100 1
b100010 7
1"
#110000
b1000101 1
1'
0"
1#
#112000
b11000 5
b10010001101000101 -
b10010001101000101 2
b10001011 1
b1000101 7
1"
#114000
b10001010 1
0'
0"
0#
#116000
b11001 5
b10100 1
b1010 7
1"
#118000
b10101 1
1'
0"
1#
#120000
b11010 5
b101011 1
b10101 7
1"
#122000
0"
#124000
b11011 5
b1010111 1
b101011 7
1"
#126000
b1010110 1
0'
0"
0#
#128000
b11100 5
b10101100 1
b1010110 7
1"
#130000
0"
#132000
b11101 5
b1011000 1
b101100 7
1"
#134000
b1011001 1
1'
0"
1#
#136000
b11110 5
b10110011 1
b1011001 7
1"
#138000
0"
#140000
b11111 5
b1100111 1
b110011 7
1"
#142000
0"
#144000
b1100111 +
b1100111 0
b10010001101000101 .
b100000 5
1)
1,
b1100111 *
b1100111 4
b11001111 1
b1100111 7
1"
#146000
0/
0$
0"
#148000
bx +
bx 0
bx .
b100001 5
0)
0,
b10011111 1
b1001111 7
1"
#150000
1/
1$
b10011110 1
0'
0"
0#
#152000
b100010 5
b111100 1
b11110 7
1"
#154000
0"
#156000
b100011 5
b1111000 1
b111100 7
1"
#158000
0"
#160000
b100100 5
b11110000 1
b1111000 7
1"
#162000
b11110001 1
1'
0"
1#
#164000
b100101 5
b11100011 1
b1110001 7
1"
#166000
b11100010 1
0'
0"
0#
#168000
b100110 5
b11000100 1
b1100010 7
1"
#170000
0"
#172000
b100111 5
b10001000 1
b1000100 7
1"
#174000
b10001001 1
1'
0"
1#
#176000
b10001001 +
b10001001 0
b10010001101000110 .
b100000 5
1)
1,
b10001001 *
b10001001 4
b10010001101000110 -
b10010001101000110 2
b10011 1
b1001 7
1"
#178000
0/
0$
0"
#180000
bx +
bx 0
bx .
b100001 5
0)
0,
b100111 1
b10011 7
1"
#182000
1/
1$
b100110 1
0'
0"
0#
#184000
b100010 5
b1001100 1
b100110 7
1"
#186000
b1001101 1
1'
0"
1#
#188000
b100011 5
b10011011 1
b1001101 7
1"
#190000
b10011010 1
0'
0"
0#
#192000
b100100 5
b110100 1
b11010 7
1"
#194000
b110101 1
1'
0"
1#
#196000
b100101 5
b1101011 1
b110101 7
1"
#198000
b1101010 1
0'
0"
0#
#200000
b100110 5
b11010100 1
b1101010 7
1"
#202000
b11010101 1
1'
0"
1#
#204000
b100111 5
b10101011 1
b1010101 7
1"
#206000
0"
#208000
b10101011 +
b10101011 0
b10010001101000111 .
b100000 5
1)
1,
b10101011 *
b10101011 4
b10010001101000111 -
b10010001101000111 2
b1010111 1
b101011 7
1"
#210000
0/
0$
0"
#212000
1/
bx +
bx 0
bx .
1$
b1 1
b0 7
0)
b0 *
b0 4
0,
b0 -
b0 2
b0 5
1!
#218000
0!
#220000
b1 5
b11 1
b1 7
1"
#222000
b10 1
0'
0"
0#
#224000
b10 5
b100 1
b10 7
1"
#226000
0"
#228000
b11 5
b1000 1
b100 7
1"
#230000
0"
#232000
b100 5
b10000 1
b1000 7
1"
#234000
0"
#236000
b101 5
b100000 1
b10000 7
1"
#238000
0"
#240000
b110 5
b1000000 1
b100000 7
1"
#242000
0"
#244000
b111 5
b10000000 1
b1000000 7
1"
#246000
b10000001 1
1'
0"
1#
#248000
b1000 5
b10000000000000000 -
b10000000000000000 2
16
b11 1
b1 7
1"
#250000
b10 1
0'
0"
0#
#252000
b1001 5
b100 1
b10 7
1"
#254000
0"
#256000
b1010 5
b1000 1
b100 7
1"
#258000
b1001 1
1'
0"
1#
#260000
b1011 5
b10011 1
b1001 7
1"
#262000
b10010 1
0'
0"
0#
#264000
b1100 5
b100100 1
b10010 7
1"
#266000
0"
#268000
b1101 5
b1001000 1
b100100 7
1"
#270000
0"
#272000
b1110 5
b10010000 1
b1001000 7
1"
#274000
b10010001 1
1'
0"
1#
#276000
b1111 5
b100011 1
b10001 7
1"
#278000
0"
#280000
b10000 5
b10010001100000000 -
b10010001100000000 2
b1000111 1
b100011 7
1"
#282000
b1000110 1
0'
0"
0#
#284000
b10001 5
b10001100 1
b1000110 7
1"
#286000
b10001101 1
1'
0"
1#
#288000
b10010 5
b11011 1
b1101 7
1"
#290000
b11010 1
0'
0"
0#
#292000
b10011 5
b110100 1
b11010 7
1"
#294000
0"
#296000
b10100 5
b1101000 1
b110100 7
1"
#298000
0"
#300000
b10101 5
b11010000 1
b1101000 7
1"
#302000
b11010001 1
1'
0"
1#
#304000
b10110 5
b10100011 1
b1010001 7
1"
#306000
b10100010 1
0'
0"
0#
#308000
b10111 5
b1000100 1
b100010 7
1"
#310000
b1000101 1
1'
0"
1#
#312000
b1000101 +
b1000101 0
0/
b10010001101000101 .
b11000 5
0(
1,
b10010001101000101 -
b10010001101000101 2
b10001011 1
b1000101 7
1"
#314000
b1000101 3
b10001010 1
0'
0"
0#
#316000
bx +
bx 0
1/
bx .
b11001 5
1%
1(
0,
b10100 1
b1010 7
1"
#318000
b10101 1
1'
1&
b10001010 3
0"
#320000
b11010 5
1%
b101011 1
b10101 7
1"
#322000
b101010 1
0'
0&
b10100 3
0"
#324000
b11011 5
1%
b1010100 1
b101010 7
1"
#326000
b101000 3
0"
#328000
b11100 5
1%
b10101000 1
b1010100 7
1"
#330000
b1010000 3
0"
#332000
b11101 5
1%
b1010000 1
b101000 7
1"
#334000
b1010001 1
1'
1&
b10100000 3
0"
#336000
b11110 5
1%
b10100011 1
b1010001 7
1"
#338000
b10100010 1
0'
0&
b1000000 3
0"
#340000
b11111 5
1%
b1000100 1
b100010 7
1"
#342000
b1000101 1
1'
1&
b10000000 3
0"
#344000
b1000110 +
b1000110 0
0/
b10010001101000110 .
b100000 5
0(
1,
b10010001101000110 -
b10010001101000110 2
1%
b10001011 1
b1000101 7
1"
#346000
b10001010 1
0'
0&
b1000110 3
0"
#348000
bx +
bx 0
1/
bx .
b100001 5
1%
1(
0,
b10100 1
b1010 7
1"
#350000
b10101 1
1'
1&
b10001100 3
0"
#352000
b100010 5
1%
b101011 1
b10101 7
1"
#354000
b101010 1
0'
0&
b11000 3
0"
#356000
b100011 5
1%
b1010100 1
b101010 7
1"
#358000
b110000 3
0"
#360000
b100100 5
1%
b10101000 1
b1010100 7
1"
#362000
b1100000 3
0"
#364000
b100101 5
1%
b1010000 1
b101000 7
1"
#366000
b1010001 1
1'
1&
b11000000 3
0"
#368000
b100110 5
1%
b10100011 1
b1010001 7
1"
#370000
b10000000 3
0"
#372000
b100111 5
1%
b1000111 1
b100011 7
1"
#374000
b1000110 1
0'
0&
b0 3
0"
#376000
b1000111 +
b1000111 0
0/
b10010001101000111 .
b100000 5
0(
1,
b10010001101000111 -
b10010001101000111 2
1%
b10001100 1
b1000110 7
1"
#378000
b1000111 3
0"
#380000
bx +
bx 0
1/
bx .
b100001 5
1%
1(
0,
b11000 1
b1100 7
1"
#382000
b11001 1
1'
1&
b10001110 3
0"
#384000
b100010 5
1%
b110011 1
b11001 7
1"
#386000
b110010 1
0'
0&
b11100 3
0"
#388000
b100011 5
1%
b1100100 1
b110010 7
1"
#390000
b111000 3
0"
#392000
b100100 5
1%
b11001000 1
b1100100 7
1"
#394000
b1110000 3
0"
#396000
b100101 5
1%
b10010000 1
b1001000 7
1"
#398000
b10010001 1
1'
1&
b11100000 3
0"
#400000
b100110 5
1%
b100011 1
b10001 7
1"
#402000
b11000000 3
0"
#404000
b100111 5
1%
b1000111 1
b100011 7
1"
#406000
b10000000 3
0"
#408000
b1001000 +
b1001000 0
0/
b10010001101001000 .
b100000 5
0(
1,
b10010001101001000 -
b10010001101001000 2
1%
b10001111 1
b1000111 7
1"
#410000
b10001110 1
0'
0&
b1001000 3
0"
#412000
bx +
bx 0
1/
bx .
1(
0%
b0 1
b0 7
b0 3
0,
b0 -
b0 2
06
b0 5
1!
